[{
  "history_id" : "mb5ot7c32v2",
  "history_input" : "No code saved",
  "history_output" : "Skipped",
  "history_begin_time" : 1707883208696,
  "history_end_time" : 1707883208696,
  "history_notes" : null,
  "history_process" : "78vedq",
  "host_id" : "100001",
  "indicator" : "Skipped"
},{
  "history_id" : "3z4ftzz1j30",
  "history_input" : "No code saved",
  "history_output" : "Skipped",
  "history_begin_time" : 1707883208735,
  "history_end_time" : 1707883208735,
  "history_notes" : null,
  "history_process" : "mxpyqt",
  "host_id" : "100001",
  "indicator" : "Skipped"
},{
  "history_id" : "yhu40gltrtm",
  "history_input" : "No code saved",
  "history_output" : "Skipped",
  "history_begin_time" : 1707883208737,
  "history_end_time" : 1707883208737,
  "history_notes" : null,
  "history_process" : "rauqsh",
  "host_id" : "100001",
  "indicator" : "Skipped"
},{
  "history_id" : "n895bn1tjml",
  "history_input" : "No code saved",
  "history_output" : "Skipped",
  "history_begin_time" : 1707883208739,
  "history_end_time" : 1707883208739,
  "history_notes" : null,
  "history_process" : "u7xh2p",
  "host_id" : "100001",
  "indicator" : "Skipped"
},{
  "history_id" : "ioj3mhjx7af",
  "history_input" : "No code saved",
  "history_output" : "Skipped",
  "history_begin_time" : 1707883208740,
  "history_end_time" : 1707883208740,
  "history_notes" : null,
  "history_process" : "e8k4wq",
  "host_id" : "100001",
  "indicator" : "Skipped"
},{
  "history_id" : "yhorgg1bvs6",
  "history_input" : null,
  "history_output" : "No value present",
  "history_begin_time" : 1707883216054,
  "history_end_time" : 1707883216342,
  "history_notes" : null,
  "history_process" : "h1qp9v",
  "host_id" : "100001",
  "indicator" : "Failed"
},{
  "history_id" : "bmpzgemchwl",
  "history_input" : "No code saved",
  "history_output" : "Skipped",
  "history_begin_time" : 1707883208759,
  "history_end_time" : 1707883208759,
  "history_notes" : null,
  "history_process" : "urd0nk",
  "host_id" : "100001",
  "indicator" : "Skipped"
},{
  "history_id" : "26hkbc7wp7u",
  "history_input" : "No code saved",
  "history_output" : "Skipped",
  "history_begin_time" : 1707883208762,
  "history_end_time" : 1707883208762,
  "history_notes" : null,
  "history_process" : "525l8q",
  "host_id" : "100001",
  "indicator" : "Skipped"
},{
  "history_id" : "1pdoigp7cad",
  "history_input" : "No code saved",
  "history_output" : "Skipped",
  "history_begin_time" : 1707883208765,
  "history_end_time" : 1707883208765,
  "history_notes" : null,
  "history_process" : "7temiv",
  "host_id" : "100001",
  "indicator" : "Skipped"
},{
  "history_id" : "wtdyhzjqmzi",
  "history_input" : "No code saved",
  "history_output" : "Skipped",
  "history_begin_time" : 1707883208768,
  "history_end_time" : 1707883208768,
  "history_notes" : null,
  "history_process" : "rmxece",
  "host_id" : "100001",
  "indicator" : "Skipped"
},{
  "history_id" : "al93484xn6c",
  "history_input" : "No code saved",
  "history_output" : "Skipped",
  "history_begin_time" : 1707883208771,
  "history_end_time" : 1707883208771,
  "history_notes" : null,
  "history_process" : "illwc1",
  "host_id" : "100001",
  "indicator" : "Skipped"
},{
  "history_id" : "meedq4y8ks8",
  "history_input" : "No code saved",
  "history_output" : "Skipped",
  "history_begin_time" : 1707883208774,
  "history_end_time" : 1707883208774,
  "history_notes" : null,
  "history_process" : "sjs5by",
  "host_id" : "100001",
  "indicator" : "Skipped"
},{
  "history_id" : "fsrthm00ci1",
  "history_input" : "No code saved",
  "history_output" : "Skipped",
  "history_begin_time" : 1707883208778,
  "history_end_time" : 1707883208778,
  "history_notes" : null,
  "history_process" : "y7nb46",
  "host_id" : "100001",
  "indicator" : "Skipped"
},{
  "history_id" : "h7din9uxizb",
  "history_input" : "No code saved",
  "history_output" : "Skipped",
  "history_begin_time" : 1707883208781,
  "history_end_time" : 1707883208781,
  "history_notes" : null,
  "history_process" : "a8p3n7",
  "host_id" : "100001",
  "indicator" : "Skipped"
},{
  "history_id" : "ix2eb71t9cj",
  "history_input" : "No code saved",
  "history_output" : "Skipped",
  "history_begin_time" : 1707883208784,
  "history_end_time" : 1707883208784,
  "history_notes" : null,
  "history_process" : "smsdr0",
  "host_id" : "100001",
  "indicator" : "Skipped"
},{
  "history_id" : "4zxwyhwswz7",
  "history_input" : "No code saved",
  "history_output" : "Skipped",
  "history_begin_time" : 1707883208787,
  "history_end_time" : 1707883208787,
  "history_notes" : null,
  "history_process" : "4i0sop",
  "host_id" : "100001",
  "indicator" : "Skipped"
},{
  "history_id" : "66rorkzfrm0",
  "history_input" : null,
  "history_output" : "No value present",
  "history_begin_time" : 1707883214893,
  "history_end_time" : 1707883215217,
  "history_notes" : null,
  "history_process" : "b63prf",
  "host_id" : "100001",
  "indicator" : "Failed"
},{
  "history_id" : "bmnt4opoxpb",
  "history_input" : "No code saved",
  "history_output" : "Skipped",
  "history_begin_time" : 1707883208805,
  "history_end_time" : 1707883208805,
  "history_notes" : null,
  "history_process" : "zh38b6",
  "host_id" : "100001",
  "indicator" : "Skipped"
},{
  "history_id" : "u7io0u0a3jl",
  "history_input" : "No code saved",
  "history_output" : "Skipped",
  "history_begin_time" : 1707883208814,
  "history_end_time" : 1707883208814,
  "history_notes" : null,
  "history_process" : "wdh394",
  "host_id" : "100001",
  "indicator" : "Skipped"
},{
  "history_id" : "m0ofqkdev3e",
  "history_input" : "No code saved",
  "history_output" : "Skipped",
  "history_begin_time" : 1707883208823,
  "history_end_time" : 1707883208823,
  "history_notes" : null,
  "history_process" : "p87wh1",
  "host_id" : "100001",
  "indicator" : "Skipped"
},{
  "history_id" : "0t37kjpards",
  "history_input" : "No code saved",
  "history_output" : "Skipped",
  "history_begin_time" : 1707883208832,
  "history_end_time" : 1707883208832,
  "history_notes" : null,
  "history_process" : "ilbqzg",
  "host_id" : "100001",
  "indicator" : "Skipped"
},{
  "history_id" : "4dd5e2lw1rw",
  "history_input" : "No code saved",
  "history_output" : "Skipped",
  "history_begin_time" : 1707883208847,
  "history_end_time" : 1707883208847,
  "history_notes" : null,
  "history_process" : "do86ae",
  "host_id" : "100001",
  "indicator" : "Skipped"
},{
  "history_id" : "8p8ji0f7vwz",
  "history_input" : "No code saved",
  "history_output" : "Skipped",
  "history_begin_time" : 1707883208860,
  "history_end_time" : 1707883208860,
  "history_notes" : null,
  "history_process" : "gkhtc0",
  "host_id" : "100001",
  "indicator" : "Skipped"
},{
  "history_id" : "13w449insq6",
  "history_input" : "No code saved",
  "history_output" : "Skipped",
  "history_begin_time" : 1707883208870,
  "history_end_time" : 1707883208870,
  "history_notes" : null,
  "history_process" : "lbd6cp",
  "host_id" : "100001",
  "indicator" : "Skipped"
},{
  "history_id" : "sr4lzoh8m53",
  "history_input" : "No code saved",
  "history_output" : "Skipped",
  "history_begin_time" : 1707883208879,
  "history_end_time" : 1707883208879,
  "history_notes" : null,
  "history_process" : "br9etb",
  "host_id" : "100001",
  "indicator" : "Skipped"
},{
  "history_id" : "tm39x6h2ype",
  "history_input" : "No code saved",
  "history_output" : "Skipped",
  "history_begin_time" : 1707883208887,
  "history_end_time" : 1707883208887,
  "history_notes" : null,
  "history_process" : "c2xkhz",
  "host_id" : "100001",
  "indicator" : "Skipped"
},{
  "history_id" : "412x19hgiha",
  "history_input" : "No code saved",
  "history_output" : "Skipped",
  "history_begin_time" : 1707883208895,
  "history_end_time" : 1707883208895,
  "history_notes" : null,
  "history_process" : "doinnd",
  "host_id" : "100001",
  "indicator" : "Skipped"
},{
  "history_id" : "lmbvsqu3o3r",
  "history_input" : "No code saved",
  "history_output" : "Skipped",
  "history_begin_time" : 1707883208902,
  "history_end_time" : 1707883208902,
  "history_notes" : null,
  "history_process" : "b7a4fu",
  "host_id" : "100001",
  "indicator" : "Skipped"
},{
  "history_id" : "9cbr5ji4d77",
  "history_input" : "No code saved",
  "history_output" : "Skipped",
  "history_begin_time" : 1707883208909,
  "history_end_time" : 1707883208909,
  "history_notes" : null,
  "history_process" : "gnpbdq",
  "host_id" : "100001",
  "indicator" : "Skipped"
},{
  "history_id" : "7uyiw0rku0k",
  "history_input" : "No code saved",
  "history_output" : "Skipped",
  "history_begin_time" : 1707883208918,
  "history_end_time" : 1707883208918,
  "history_notes" : null,
  "history_process" : "oon4sb",
  "host_id" : "100001",
  "indicator" : "Skipped"
},{
  "history_id" : "9301i2kymmh",
  "history_input" : "No code saved",
  "history_output" : "Skipped",
  "history_begin_time" : 1707883208926,
  "history_end_time" : 1707883208926,
  "history_notes" : null,
  "history_process" : "fa7e4u",
  "host_id" : "100001",
  "indicator" : "Skipped"
},{
  "history_id" : "gq07hzcrz4k",
  "history_input" : null,
  "history_output" : "No value present",
  "history_begin_time" : 1707883213225,
  "history_end_time" : 1707883213511,
  "history_notes" : null,
  "history_process" : "drwmbo",
  "host_id" : "100001",
  "indicator" : "Failed"
},{
  "history_id" : "8k06awwficl",
  "history_input" : "No code saved",
  "history_output" : "Skipped",
  "history_begin_time" : 1707883208947,
  "history_end_time" : 1707883208947,
  "history_notes" : null,
  "history_process" : "2n7b06",
  "host_id" : "100001",
  "indicator" : "Skipped"
},{
  "history_id" : "d3kmsjvgf5h",
  "history_input" : "No code saved",
  "history_output" : "Skipped",
  "history_begin_time" : 1707883208958,
  "history_end_time" : 1707883208958,
  "history_notes" : null,
  "history_process" : "bwdy3s",
  "host_id" : "100001",
  "indicator" : "Skipped"
},{
  "history_id" : "0jjrcmnzc1y",
  "history_input" : null,
  "history_output" : "No value present",
  "history_begin_time" : 1707883217771,
  "history_end_time" : 1707883218048,
  "history_notes" : null,
  "history_process" : "2wkl6e",
  "host_id" : "100001",
  "indicator" : "Failed"
},{
  "history_id" : "gblrrnxsvef",
  "history_input" : null,
  "history_output" : "No value present",
  "history_begin_time" : 1707883218880,
  "history_end_time" : 1707883219142,
  "history_notes" : null,
  "history_process" : "i2fynz",
  "host_id" : "100001",
  "indicator" : "Failed"
},{
  "history_id" : "u6w27m0qzx0",
  "history_input" : "No code saved",
  "history_output" : "Skipped",
  "history_begin_time" : 1707883208989,
  "history_end_time" : 1707883208989,
  "history_notes" : null,
  "history_process" : "2o6cp8",
  "host_id" : "100001",
  "indicator" : "Skipped"
},{
  "history_id" : "k9wctozaxo6",
  "history_input" : null,
  "history_output" : "No value present",
  "history_begin_time" : 1707883212070,
  "history_end_time" : 1707883212349,
  "history_notes" : null,
  "history_process" : "0n26v2",
  "host_id" : "100001",
  "indicator" : "Failed"
},{
  "history_id" : "7oc8a7gpdo2",
  "history_input" : "No code saved",
  "history_output" : "Skipped",
  "history_begin_time" : 1707883209014,
  "history_end_time" : 1707883209014,
  "history_notes" : null,
  "history_process" : "rvqv35",
  "host_id" : "100001",
  "indicator" : "Skipped"
},{
  "history_id" : "3pdl7bzg1mm",
  "history_input" : "No code saved",
  "history_output" : "Skipped",
  "history_begin_time" : 1707883209024,
  "history_end_time" : 1707883209024,
  "history_notes" : null,
  "history_process" : "vo8bc9",
  "host_id" : "100001",
  "indicator" : "Skipped"
},{
  "history_id" : "agmedzq3wul",
  "history_input" : "No code saved",
  "history_output" : "Skipped",
  "history_begin_time" : 1707883209036,
  "history_end_time" : 1707883209036,
  "history_notes" : null,
  "history_process" : "6evkh4",
  "host_id" : "100001",
  "indicator" : "Skipped"
},{
  "history_id" : "s26o9mg3bha",
  "history_input" : "No code saved",
  "history_output" : "Skipped",
  "history_begin_time" : 1707883209049,
  "history_end_time" : 1707883209049,
  "history_notes" : null,
  "history_process" : "76ewp5",
  "host_id" : "100001",
  "indicator" : "Skipped"
},{
  "history_id" : "dqygb3ijltc",
  "history_input" : "No code saved",
  "history_output" : "Skipped",
  "history_begin_time" : 1707883209060,
  "history_end_time" : 1707883209060,
  "history_notes" : null,
  "history_process" : "5wzgx5",
  "host_id" : "100001",
  "indicator" : "Skipped"
},{
  "history_id" : "rwb986burl6",
  "history_input" : "No code saved",
  "history_output" : "Skipped",
  "history_begin_time" : 1707883209070,
  "history_end_time" : 1707883209070,
  "history_notes" : null,
  "history_process" : "d4zcq6",
  "host_id" : "100001",
  "indicator" : "Skipped"
},{
  "history_id" : "tf675v5gl37",
  "history_input" : "No code saved",
  "history_output" : "Skipped",
  "history_begin_time" : 1707883209081,
  "history_end_time" : 1707883209081,
  "history_notes" : null,
  "history_process" : "6x6myw",
  "host_id" : "100001",
  "indicator" : "Skipped"
},{
  "history_id" : "cqqzrd3fvox",
  "history_input" : "No code saved",
  "history_output" : "Skipped",
  "history_begin_time" : 1707883209091,
  "history_end_time" : 1707883209091,
  "history_notes" : null,
  "history_process" : "r4knm9",
  "host_id" : "100001",
  "indicator" : "Skipped"
},{
  "history_id" : "zejlwe5lvfp",
  "history_input" : "No code saved",
  "history_output" : "Skipped",
  "history_begin_time" : 1707883209102,
  "history_end_time" : 1707883209102,
  "history_notes" : null,
  "history_process" : "9c573m",
  "host_id" : "100001",
  "indicator" : "Skipped"
},{
  "history_id" : "rpht3ap5bbd",
  "history_input" : "No code saved",
  "history_output" : "Skipped",
  "history_begin_time" : 1707883209111,
  "history_end_time" : 1707883209111,
  "history_notes" : null,
  "history_process" : "ee5ur4",
  "host_id" : "100001",
  "indicator" : "Skipped"
},{
  "history_id" : "376ddlpmv8o",
  "history_input" : "No code saved",
  "history_output" : "Skipped",
  "history_begin_time" : 1707883209122,
  "history_end_time" : 1707883209122,
  "history_notes" : null,
  "history_process" : "f03i7p",
  "host_id" : "100001",
  "indicator" : "Skipped"
},{
  "history_id" : "embcl009w84",
  "history_input" : "No code saved",
  "history_output" : "Skipped",
  "history_begin_time" : 1707883209132,
  "history_end_time" : 1707883209132,
  "history_notes" : null,
  "history_process" : "83d2yv",
  "host_id" : "100001",
  "indicator" : "Skipped"
},{
  "history_id" : "l6yi8jatt9h",
  "history_input" : "No code saved",
  "history_output" : "Skipped",
  "history_begin_time" : 1707883209141,
  "history_end_time" : 1707883209141,
  "history_notes" : null,
  "history_process" : "j8swco",
  "host_id" : "100001",
  "indicator" : "Skipped"
},{
  "history_id" : "zun9kdmwkt0",
  "history_input" : "No code saved",
  "history_output" : "Skipped",
  "history_begin_time" : 1707883209149,
  "history_end_time" : 1707883209149,
  "history_notes" : null,
  "history_process" : "pnr64x",
  "host_id" : "100001",
  "indicator" : "Skipped"
},{
  "history_id" : "uqg47df81z6",
  "history_input" : "No code saved",
  "history_output" : "Skipped",
  "history_begin_time" : 1707883209160,
  "history_end_time" : 1707883209160,
  "history_notes" : null,
  "history_process" : "qg80lj",
  "host_id" : "100001",
  "indicator" : "Skipped"
},{
  "history_id" : "9eoisme5fhu",
  "history_input" : "No code saved",
  "history_output" : "Skipped",
  "history_begin_time" : 1707883209170,
  "history_end_time" : 1707883209170,
  "history_notes" : null,
  "history_process" : "ggy7gf",
  "host_id" : "100001",
  "indicator" : "Skipped"
},{
  "history_id" : "t9e3sce1if8",
  "history_input" : null,
  "history_output" : "No value present",
  "history_begin_time" : 1707883210071,
  "history_end_time" : 1707883210668,
  "history_notes" : null,
  "history_process" : "c2qa9u",
  "host_id" : "100001",
  "indicator" : "Failed"
},{
  "history_id" : "1nm8g3n54ah",
  "history_input" : "No code saved",
  "history_output" : "Skipped",
  "history_begin_time" : 1707883209195,
  "history_end_time" : 1707883209195,
  "history_notes" : null,
  "history_process" : "lnrsop",
  "host_id" : "100001",
  "indicator" : "Skipped"
},{
  "history_id" : "vrwy3plsbcf",
  "history_input" : "No code saved",
  "history_output" : "Skipped",
  "history_begin_time" : 1707883209207,
  "history_end_time" : 1707883209207,
  "history_notes" : null,
  "history_process" : "c8isgf",
  "host_id" : "100001",
  "indicator" : "Skipped"
}]
