[{
  "history_id" : "od39bpxjsp4",
  "history_input" : "# Data preparation for Sentinel 1\n\nprint(\"prepare Sentinel 1 into .csv\")\n",
  "history_output" : "prepare Sentinel 1 into .csv\n",
  "history_begin_time" : 1642454673129,
  "history_end_time" : 1642454673375,
  "history_notes" : null,
  "history_process" : "m3bqdb",
  "host_id" : "100001",
  "indicator" : "Done"
},{
  "history_id" : "b6wvr2arn6t",
  "history_input" : "# Data Preparation for Sentinel 2\n\nprint(\"Prepare sentinel 2 into .csv\")\n\n",
  "history_output" : "Prepare sentinel 2 into .csv\n",
  "history_begin_time" : 1642454673149,
  "history_end_time" : 1642454673425,
  "history_notes" : null,
  "history_process" : "78vedq",
  "host_id" : "100001",
  "indicator" : "Done"
},{
  "history_id" : "sz0cab4cf02",
  "history_input" : "# Data Preparation MODIS\n\nprint(\"Prepare MODIS into .csv\")\n",
  "history_output" : "Prepare MODIS into .csv\n",
  "history_begin_time" : 1642454672834,
  "history_end_time" : 1642454673345,
  "history_notes" : null,
  "history_process" : "ob2m37",
  "host_id" : "100001",
  "indicator" : "Done"
},{
  "history_id" : "vuwfyp6evrq",
  "history_input" : "# Create LSTM model\n\nprint(\"Create LSTM\")\n\n",
  "history_output" : "Create LSTM\n",
  "history_begin_time" : 1642454672931,
  "history_end_time" : 1642454673345,
  "history_notes" : null,
  "history_process" : "mxpyqt",
  "host_id" : "100001",
  "indicator" : "Done"
},{
  "history_id" : "8zmd5pylfby",
  "history_input" : "# Random Forest model creation and save to file\n\nprint(\"create random forest\")\n\n",
  "history_output" : "create random forest\n",
  "history_begin_time" : 1642454673134,
  "history_end_time" : 1642454673449,
  "history_notes" : null,
  "history_process" : "c2xkhz",
  "host_id" : "100001",
  "indicator" : "Done"
},{
  "history_id" : "p6rpx0olh5y",
  "history_input" : "# GhostNet\n\nprint(\"Create GhostNet\")\n\n",
  "history_output" : "Create GhostNet\n",
  "history_begin_time" : 1642454674465,
  "history_end_time" : 1642454674599,
  "history_notes" : null,
  "history_process" : "rauqsh",
  "host_id" : "100001",
  "indicator" : "Done"
},{
  "history_id" : "r6aofxtw0jy",
  "history_input" : "# Find the best model\n\n",
  "history_output" : "",
  "history_begin_time" : 1642454680795,
  "history_end_time" : 1642454680940,
  "history_notes" : null,
  "history_process" : "mi3e5n",
  "host_id" : "100001",
  "indicator" : "Done"
},{
  "history_id" : "ky8hwp680qh",
  "history_input" : "# Integrate all the datasets into one training dataset\n\nprint(\"integrating datasets into one dataset\")\n\n",
  "history_output" : "integrating datasets into one dataset\n",
  "history_begin_time" : 1642454674489,
  "history_end_time" : 1642454674629,
  "history_notes" : null,
  "history_process" : "u7xh2p",
  "host_id" : "100001",
  "indicator" : "Done"
},{
  "history_id" : "67w94uwybuf",
  "history_input" : "# Deploy model to service\n\nprint(\"deploy model to service\")\n",
  "history_output" : "deploy model to service\n",
  "history_begin_time" : 1642454682946,
  "history_end_time" : 1642454683090,
  "history_notes" : null,
  "history_process" : "2wkl6e",
  "host_id" : "100001",
  "indicator" : "Done"
},{
  "history_id" : "pw8xdgyyboc",
  "history_input" : "# Predict results using the model\n\nprint(\"feed data into the service and monitor the results\")\n\n",
  "history_output" : "feed data into the service and monitor the results\n",
  "history_begin_time" : 1642454685029,
  "history_end_time" : 1642454685159,
  "history_notes" : null,
  "history_process" : "i2fynz",
  "host_id" : "100001",
  "indicator" : "Done"
},{
  "history_id" : "fzt6qh681sa",
  "history_input" : "# Train Model\n\nprint(\"Train Models\")\n",
  "history_output" : "Train Models\n",
  "history_begin_time" : 1642454676510,
  "history_end_time" : 1642454676709,
  "history_notes" : null,
  "history_process" : "e8k4wq",
  "host_id" : "100001",
  "indicator" : "Done"
},{
  "history_id" : "wd6i29sq7zb",
  "history_input" : "# Test models\n\nprint(\"test models\")\n\n",
  "history_output" : "test models\n",
  "history_begin_time" : 1642454678735,
  "history_end_time" : 1642454678867,
  "history_notes" : null,
  "history_process" : "h1qp9v",
  "host_id" : "100001",
  "indicator" : "Done"
}]
